{
  "project_info": {
    "project_number": "877934920921",
    "project_id": "shukla-exp-manager",
    "storage_bucket": "shukla-exp-manager.firebasestorage.app"
  },
  "client": [
    {
      "client_info": {
        "mobilesdk_app_id": "1:877934920921:android:e770d3aaab5b45d482aac8",
        "android_client_info": {
          "package_name": "shukla_exp.manager"
        }
      },
      "oauth_client": [],
      "api_key": [
        {
          "current_key": "AIzaSyD4AshyOE1VvfhcvSJEKC89GUN3M5QOu1Y"
        }
      ],
      "services": {
        "appinvite_service": {
          "other_platform_oauth_client": []
        }
      }
    }
  ],
  "configuration_version": "1"
}